mdutil/__init__.py
mdutil/__main__.py
mdutil/version.py
mdutil/cli/__init__.py
mdutil/cli/genmap.py
mdutil/cli/log.py
mdutil/cli/main.py
mdutil/cli/params.py
mdutil/cli/utils.py
mdutil/cli/version.py
mdutil/core/__init__.py
mdutil/core/exceptions.py
mdutil/core/map_builder.py
mdutil/core/img/__init__.py
mdutil/core/img/palette.py
mdutil/core/img/tileset.py
mdutil/core/tmx/__init__.py
mdutil/core/tmx/api/__init__.py
mdutil/core/tmx/api/map.py
mdutil/core/tmx/model/__init__.py
mdutil/core/tmx/model/layer.py
mdutil/core/tmx/model/map.py
mdutil/core/tmx/model/object.py
mdutil/core/tmx/model/property.py
mdutil/core/tmx/model/tileset.py
mdutil/core/tmx/parser/__init__.py
mdutil/core/tmx/parser/tmx_parser.py
mdutil/core/tmx/parser/tsx_parser.py
mdutil/core/util/__init__.py
mdutil/core/util/data_type.py
mdutil/core/util/helper.py
mdutilities-0.1.1.dist-info/LICENSE
mdutilities-0.1.1.dist-info/METADATA
mdutilities-0.1.1.dist-info/WHEEL
mdutilities-0.1.1.dist-info/entry_points.txt
mdutilities-0.1.1.dist-info/top_level.txt
mdutilities-0.1.1.dist-info/RECORD
