Metadata-Version: 2.1
Name: mdutilities
Version: 0.1.1
Summary: A command line tool for megadrive homebrew developers
Author-email: Pablo Porta <paspallasdev@gmail.com>
Maintainer-email: Pablo Porta <paspallasdev@gmail.com>
License: MIT License
Project-URL: Issues, https://github.com/paspallas/mdutil/issues
Project-URL: Homepage, https://github.com/paspallas/mdutil
Project-URL: Documentation, https://mdutil.readthedocs.io
Keywords: homebrew,cli,megadrive,tiled,tool,exporter,templates,mako
Classifier: Development Status :: 3 - Alpha
Classifier: Environment :: Console
Classifier: Intended Audience :: End Users/Desktop
Classifier: Operating System :: OS Independent
Classifier: Programming Language :: Python :: 3
Classifier: Programming Language :: Python :: 3.10
Classifier: Programming Language :: Python :: 3.11
Classifier: Programming Language :: Python :: 3.12
Requires-Python: >=3.10
License-File: LICENSE
Requires-Dist: click >=8.1.7
Requires-Dist: numpy >=2.1.2
Requires-Dist: pillow >=11.0.0
Requires-Dist: zstandard >=0.23.0
